pydantic_apply/__init__.py
pydantic_apply/_compat.py
pydantic_apply/apply.py
pydantic_apply/py.typed
pydantic_apply/utils.py
pydantic_apply-0.8.1.dist-info/licenses/LICENSE
pydantic_apply-0.8.1.dist-info/WHEEL
pydantic_apply-0.8.1.dist-info/METADATA
pydantic_apply-0.8.1.dist-info/RECORD
