Metadata-Version: 2.4
Name: pydantic-apply
Version: 0.8.1
Summary: Apply changes as patches to pydantic models.
Author: TEAM23 GmbH
Author-email: TEAM23 GmbH <info@team23.de>
License-Expression: MIT
License-File: LICENSE
Requires-Dist: pydantic>=2.0.0,<3.0.0
Requires-Python: >=3.10
Project-URL: Repository, https://github.com/team23/pydantic-apply
